radish/__init__.py
radish/exceptions.py
radish/pool.py
radish/radish.py
radish/typings.py
radish/utils.py
radish_router-0.1.1.dist-info/LICENSE
radish_router-0.1.1.dist-info/WHEEL
radish_router-0.1.1.dist-info/METADATA
radish_router-0.1.1.dist-info/RECORD
